invenio_config_tugraz/__init__.py
invenio_config_tugraz/components.py
invenio_config_tugraz/config.py
invenio_config_tugraz/ext.py
invenio_config_tugraz/facets.py
invenio_config_tugraz/utils.py
invenio_config_tugraz/views.py
invenio_config_tugraz/custom_fields/__init__.py
invenio_config_tugraz/notifications/__init__.py
invenio_config_tugraz/notifications/builders.py
invenio_config_tugraz/permissions/__init__.py
invenio_config_tugraz/permissions/generators.py
invenio_config_tugraz/permissions/policies.py
invenio_config_tugraz/permissions/roles.py
invenio_config_tugraz/requests/__init__.py
invenio_config_tugraz/requests/events.py
invenio_config_tugraz/restrictions/access_right/access_right.csv
invenio_config_tugraz/restrictions/access_right/access_right_limit.csv
invenio_config_tugraz/static/documents/TUGraz_Repository_General_Data_Protection_Rights_de.pdf
invenio_config_tugraz/static/documents/TUGraz_Repository_General_Data_Protection_Rights_en.pdf
invenio_config_tugraz/static/documents/TUGraz_Repository_Guide_01_de.pdf
invenio_config_tugraz/static/documents/TUGraz_Repository_Guide_01_en.pdf
invenio_config_tugraz/static/documents/TUGraz_Repository_Guide_02.1_de.pdf
invenio_config_tugraz/static/documents/TUGraz_Repository_Guide_02.1_en.pdf
invenio_config_tugraz/static/documents/TUGraz_Repository_Guide_02_de.pdf
invenio_config_tugraz/static/documents/TUGraz_Repository_Guide_02_en.pdf
invenio_config_tugraz/static/documents/TUGraz_Repository_Terms_And_Conditions_de.pdf
invenio_config_tugraz/static/documents/TUGraz_Repository_Terms_And_Conditions_en.pdf
invenio_config_tugraz/templates/security/email/welcome.txt
invenio_config_tugraz/translations/.gitkeep
invenio_config_tugraz/translations/messages.pot
invenio_config_tugraz/translations/de/LC_MESSAGES/messages.mo
invenio_config_tugraz/translations/de/LC_MESSAGES/messages.po
invenio_config_tugraz-0.13.2.dist-info/licenses/AUTHORS.rst
invenio_config_tugraz-0.13.2.dist-info/licenses/LICENSE
invenio_config_tugraz-0.13.2.dist-info/METADATA
invenio_config_tugraz-0.13.2.dist-info/WHEEL
invenio_config_tugraz-0.13.2.dist-info/entry_points.txt
invenio_config_tugraz-0.13.2.dist-info/top_level.txt
invenio_config_tugraz-0.13.2.dist-info/RECORD
