Metadata-Version: 2.4
Name: invenio-config-tugraz
Version: 0.13.2
Summary: "Invenio module that adds tugraz configs."
Home-page: https://github.com/tu-graz-library/invenio-config-tugraz
Author: "Graz University of Technology"
Author-email: info@tugraz.at
License: MIT
Keywords: invenio config TU-Graz
Platform: any
Classifier: Environment :: Web Environment
Classifier: Intended Audience :: Developers
Classifier: License :: OSI Approved :: MIT License
Classifier: Operating System :: OS Independent
Classifier: Programming Language :: Python
Classifier: Topic :: Internet :: WWW/HTTP :: Dynamic Content
Classifier: Topic :: Software Development :: Libraries :: Python Modules
Classifier: Programming Language :: Python :: 3.12
Classifier: Development Status :: 3 - Alpha
Requires-Python: >=3.12
License-File: LICENSE
License-File: AUTHORS.rst
Requires-Dist: invenio-cache>=1.1.1
Requires-Dist: invenio-i18n>=2.0.0
Requires-Dist: invenio-rdm-records<20.0.0,>=19.0.0
Requires-Dist: invenio-curations>=0.1.0
Provides-Extra: tests
Requires-Dist: invenio-app>=1.5.0; extra == "tests"
Requires-Dist: invenio-app-rdm>=13.0.0; extra == "tests"
Requires-Dist: invenio-search[opensearch2]>=2.1.0; extra == "tests"
Requires-Dist: pytest-black>=0.6.0; extra == "tests"
Requires-Dist: pytest-invenio>=2.1.0; extra == "tests"
Requires-Dist: ruff>=0.5.3; extra == "tests"
Requires-Dist: Sphinx>=4.5.0; extra == "tests"
Dynamic: license-file
